forecast_plots/__init__.py
forecast_plots/forecast_plots.py
forecast_plots/util.py
forecast_plots-1.0.dist-info/METADATA
forecast_plots-1.0.dist-info/WHEEL
forecast_plots-1.0.dist-info/top_level.txt
forecast_plots-1.0.dist-info/RECORD
