Metadata-Version: 2.1
Name: forecast_plots
Version: 1.0
Requires-Dist: pandas >=2.2.2
Requires-Dist: matplotlib >=3.9.0
Requires-Dist: numpy >=1.26.4
Requires-Dist: scipy >=1.13.1
